MANIFEST.in
setup.cfg
setup.py
kubeutils/__init__.py
kubeutils/kubeutils
kubeutils/kutils
kubeutils/kutils.py
kubeutils.egg-info/PKG-INFO
kubeutils.egg-info/SOURCES.txt
kubeutils.egg-info/dependency_links.txt
kubeutils.egg-info/not-zip-safe
kubeutils.egg-info/requires.txt
kubeutils.egg-info/top_level.txt
kubeutils/scripts/instance-group.sh
kubeutils/scripts/node-count.sh